parallax/__init__.py
parallax/askpass_client.py
parallax/askpass_server.py
parallax/callbacks.py
parallax/color.py
parallax/manager.py
parallax/psshutil.py
parallax/task.py
parallax/version.py
parallax-1.0.6.data/scripts/parallax-askpass
parallax-1.0.6.dist-info/AUTHORS
parallax-1.0.6.dist-info/COPYING
parallax-1.0.6.dist-info/METADATA
parallax-1.0.6.dist-info/WHEEL
parallax-1.0.6.dist-info/top_level.txt
parallax-1.0.6.dist-info/RECORD
